flask_sample_test/__init__.py
flask_sample_test/fields.py
flask_sample_test/manage.py
flask_sample_test/sample_test.py
flask_sample_test/utils.py
flask_sample_test/templates/__init__.py
flask_sample_test/templates/test_data.txt
flask_sample_test-0.0.5.dist-info/LICENSE
flask_sample_test-0.0.5.dist-info/METADATA
flask_sample_test-0.0.5.dist-info/WHEEL
flask_sample_test-0.0.5.dist-info/top_level.txt
flask_sample_test-0.0.5.dist-info/RECORD
