Metadata-Version: 2.1
Name: flask-sample-test
Version: 0.0.5
Summary: A sample test for project
Home-page: https://github.com/December1208/flask_sample_test
Author: JiaLe.tan
Author-email: jiale.gfi@outlook.com
License: UNKNOWN
Keywords: flask,test,sqlalchemy
Platform: UNKNOWN
Classifier: Programming Language :: Python :: 3
Classifier: License :: OSI Approved :: MIT License
Classifier: Operating System :: OS Independent
Requires-Python: >=3.7
License-File: LICENSE
Requires-Dist: flask-sqlalchemy (>=2.0)
